{
  "CREATED_BY": "Anh Vu Vo",
  "FILE_CREATION_DATE": "2019-11-15T11:38:58.928Z",
  "FLIGHT_LINES": [
    {
      "SOURCE_FILE_CREATION_DATE": "2019-08-20T00:00:00.000Z",
      "FLIGHT_ID": 1,
      "SOURCE_FILE_NAME": "10552_NYU_M2 - Scanner 1 - 190511_161348_1 - originalpoints.las",
      "NUMBER_OF_POINTS": 7015561,
      "START_TIMESTAMP": "0000-01-01T00:00:00.000Z",
      "TIME_TAG": "161348"
    },
    {
      "SOURCE_FILE_CREATION_DATE": "2019-08-20T00:00:00.000Z",
      "FLIGHT_ID": 2,
      "SOURCE_FILE_NAME": "10552_NYU_M2 - Scanner 1 - 190511_161518_1 - originalpoints.las",
      "NUMBER_OF_POINTS": 6127298,
      "START_TIMESTAMP": "0000-01-01T00:00:00.000Z",
      "TIME_TAG": "161518"
    },
    {
      "SOURCE_FILE_CREATION_DATE": "2019-08-20T00:00:00.000Z",
      "FLIGHT_ID": 3,
      "SOURCE_FILE_NAME": "10552_NYU_M2 - Scanner 1 - 190511_161726_1 - originalpoints.las",
      "NUMBER_OF_POINTS": 8725801,
      "START_TIMESTAMP": "0000-01-01T00:00:00.000Z",
      "TIME_TAG": "161726"
    },
    {
      "SOURCE_FILE_CREATION_DATE": "2019-08-20T00:00:00.000Z",
      "FLIGHT_ID": 4,
      "SOURCE_FILE_NAME": "10552_NYU_M2 - Scanner 1 - 190511_161905_1 - originalpoints.las",
      "NUMBER_OF_POINTS": 10252658,
      "START_TIMESTAMP": "0000-01-01T00:00:00.000Z",
      "TIME_TAG": "161905"
    },
    {
      "SOURCE_FILE_CREATION_DATE": "2019-08-20T00:00:00.000Z",
      "FLIGHT_ID": 5,
      "SOURCE_FILE_NAME": "10552_NYU_M2 - Scanner 1 - 190511_162124_1 - originalpoints.las",
      "NUMBER_OF_POINTS": 13410719,
      "START_TIMESTAMP": "0000-01-01T00:00:00.000Z",
      "TIME_TAG": "162124"
    },
    {
      "SOURCE_FILE_CREATION_DATE": "2019-08-20T00:00:00.000Z",
      "FLIGHT_ID": 6,
      "SOURCE_FILE_NAME": "10552_NYU_M2 - Scanner 1 - 190511_162306_1 - originalpoints.las",
      "NUMBER_OF_POINTS": 13323593,
      "START_TIMESTAMP": "0000-01-01T00:00:00.000Z",
      "TIME_TAG": "162306"
    },
    {
      "SOURCE_FILE_CREATION_DATE": "2019-08-20T00:00:00.000Z",
      "FLIGHT_ID": 7,
      "SOURCE_FILE_NAME": "10552_NYU_M2 - Scanner 1 - 190511_162537_1 - originalpoints.las",
      "NUMBER_OF_POINTS": 15926300,
      "START_TIMESTAMP": "0000-01-01T00:00:00.000Z",
      "TIME_TAG": "162537"
    },
    {
      "SOURCE_FILE_CREATION_DATE": "2019-08-20T00:00:00.000Z",
      "FLIGHT_ID": 8,
      "SOURCE_FILE_NAME": "10552_NYU_M2 - Scanner 1 - 190511_162730_1 - originalpoints.las",
      "NUMBER_OF_POINTS": 15594312,
      "START_TIMESTAMP": "0000-01-01T00:00:00.000Z",
      "TIME_TAG": "162730"
    },
    {
      "SOURCE_FILE_CREATION_DATE": "2019-08-20T00:00:00.000Z",
      "FLIGHT_ID": 9,
      "SOURCE_FILE_NAME": "10552_NYU_M2 - Scanner 1 - 190511_162957_1 - originalpoints.las",
      "NUMBER_OF_POINTS": 21955474,
      "START_TIMESTAMP": "0000-01-01T00:00:00.000Z",
      "TIME_TAG": "162957"
    },
    {
      "SOURCE_FILE_CREATION_DATE": "2019-08-20T00:00:00.000Z",
      "FLIGHT_ID": 10,
      "SOURCE_FILE_NAME": "10552_NYU_M2 - Scanner 1 - 190511_163206_1 - originalpoints.las",
      "NUMBER_OF_POINTS": 17157155,
      "START_TIMESTAMP": "0000-01-01T00:00:00.000Z",
      "TIME_TAG": "163206"
    },
    {
      "SOURCE_FILE_CREATION_DATE": "2019-08-20T00:00:00.000Z",
      "FLIGHT_ID": 12,
      "SOURCE_FILE_NAME": "10552_NYU_M2 - Scanner 1 - 190511_163634_1 - originalpoints.las",
      "NUMBER_OF_POINTS": 6643504,
      "START_TIMESTAMP": "0000-01-01T00:00:00.000Z",
      "TIME_TAG": "163634"
    },
    {
      "SOURCE_FILE_CREATION_DATE": "2019-08-20T00:00:00.000Z",
      "FLIGHT_ID": 13,
      "SOURCE_FILE_NAME": "10552_NYU_M2 - Scanner 1 - 190511_163824_1 - originalpoints.las",
      "NUMBER_OF_POINTS": 18511313,
      "START_TIMESTAMP": "0000-01-01T00:00:00.000Z",
      "TIME_TAG": "163824"
    },
    {
      "SOURCE_FILE_CREATION_DATE": "2019-08-20T00:00:00.000Z",
      "FLIGHT_ID": 14,
      "SOURCE_FILE_NAME": "10552_NYU_M2 - Scanner 1 - 190511_164039_1 - originalpoints.las",
      "NUMBER_OF_POINTS": 19326828,
      "START_TIMESTAMP": "0000-01-01T00:00:00.000Z",
      "TIME_TAG": "164039"
    },
    {
      "SOURCE_FILE_CREATION_DATE": "2019-08-20T00:00:00.000Z",
      "FLIGHT_ID": 15,
      "SOURCE_FILE_NAME": "10552_NYU_M2 - Scanner 1 - 190511_164239_1 - originalpoints.las",
      "NUMBER_OF_POINTS": 14542329,
      "START_TIMESTAMP": "0000-01-01T00:00:00.000Z",
      "TIME_TAG": "164239"
    },
    {
      "SOURCE_FILE_CREATION_DATE": "2019-08-20T00:00:00.000Z",
      "FLIGHT_ID": 16,
      "SOURCE_FILE_NAME": "10552_NYU_M2 - Scanner 1 - 190511_164445_1 - originalpoints.las",
      "NUMBER_OF_POINTS": 16217925,
      "START_TIMESTAMP": "0000-01-01T00:00:00.000Z",
      "TIME_TAG": "164445"
    },
    {
      "SOURCE_FILE_CREATION_DATE": "2019-08-20T00:00:00.000Z",
      "FLIGHT_ID": 17,
      "SOURCE_FILE_NAME": "10552_NYU_M2 - Scanner 1 - 190511_164640_1 - originalpoints.las",
      "NUMBER_OF_POINTS": 11941150,
      "START_TIMESTAMP": "0000-01-01T00:00:00.000Z",
      "TIME_TAG": "164640"
    },
    {
      "SOURCE_FILE_CREATION_DATE": "2019-08-20T00:00:00.000Z",
      "FLIGHT_ID": 18,
      "SOURCE_FILE_NAME": "10552_NYU_M2 - Scanner 1 - 190511_164845_1 - originalpoints.las",
      "NUMBER_OF_POINTS": 13053806,
      "START_TIMESTAMP": "0000-01-01T00:00:00.000Z",
      "TIME_TAG": "164845"
    },
    {
      "SOURCE_FILE_CREATION_DATE": "2019-08-20T00:00:00.000Z",
      "FLIGHT_ID": 19,
      "SOURCE_FILE_NAME": "10552_NYU_M2 - Scanner 1 - 190511_165019_1 - originalpoints.las",
      "NUMBER_OF_POINTS": 9116696,
      "START_TIMESTAMP": "0000-01-01T00:00:00.000Z",
      "TIME_TAG": "165019"
    },
    {
      "SOURCE_FILE_CREATION_DATE": "2019-08-20T00:00:00.000Z",
      "FLIGHT_ID": 20,
      "SOURCE_FILE_NAME": "10552_NYU_M2 - Scanner 1 - 190511_165210_1 - originalpoints.las",
      "NUMBER_OF_POINTS": 9645499,
      "START_TIMESTAMP": "0000-01-01T00:00:00.000Z",
      "TIME_TAG": "165210"
    },
    {
      "SOURCE_FILE_CREATION_DATE": "2019-08-20T00:00:00.000Z",
      "FLIGHT_ID": 22,
      "SOURCE_FILE_NAME": "10552_NYU_M2 - Scanner 1 - 190511_165523_1 - originalpoints.las",
      "NUMBER_OF_POINTS": 8019828,
      "START_TIMESTAMP": "0000-01-01T00:00:00.000Z",
      "TIME_TAG": "165523"
    },
    {
      "SOURCE_FILE_CREATION_DATE": "2019-08-20T00:00:00.000Z",
      "FLIGHT_ID": 1,
      "SOURCE_FILE_NAME": "10552_NYU_M2 - Scanner 1 - 190511_165636_1 - originalpoints.las",
      "NUMBER_OF_POINTS": 4239882,
      "START_TIMESTAMP": "0000-01-01T00:00:00.000Z",
      "TIME_TAG": "165636"
    },
    {
      "SOURCE_FILE_CREATION_DATE": "2019-08-20T00:00:00.000Z",
      "FLIGHT_ID": 24,
      "SOURCE_FILE_NAME": "10552_NYU_M2 - Scanner 1 - 190511_165850_1 - originalpoints.las",
      "NUMBER_OF_POINTS": 7315774,
      "START_TIMESTAMP": "0000-01-01T00:00:00.000Z",
      "TIME_TAG": "165850"
    },
    {
      "SOURCE_FILE_CREATION_DATE": "2019-08-20T00:00:00.000Z",
      "FLIGHT_ID": 25,
      "SOURCE_FILE_NAME": "10552_NYU_M2 - Scanner 1 - 190511_170032_1 - originalpoints.las",
      "NUMBER_OF_POINTS": 9180872,
      "START_TIMESTAMP": "0000-01-01T00:00:00.000Z",
      "TIME_TAG": "170032"
    },
    {
      "SOURCE_FILE_CREATION_DATE": "2019-08-20T00:00:00.000Z",
      "FLIGHT_ID": 26,
      "SOURCE_FILE_NAME": "10552_NYU_M2 - Scanner 1 - 190511_170204_1 - originalpoints.las",
      "NUMBER_OF_POINTS": 9365485,
      "START_TIMESTAMP": "0000-01-01T00:00:00.000Z",
      "TIME_TAG": "170204"
    },
    {
      "SOURCE_FILE_CREATION_DATE": "2019-08-20T00:00:00.000Z",
      "FLIGHT_ID": 27,
      "SOURCE_FILE_NAME": "10552_NYU_M2 - Scanner 1 - 190511_170324_1 - originalpoints.las",
      "NUMBER_OF_POINTS": 12284968,
      "START_TIMESTAMP": "0000-01-01T00:00:00.000Z",
      "TIME_TAG": "170324"
    },
    {
      "SOURCE_FILE_CREATION_DATE": "2019-08-20T00:00:00.000Z",
      "FLIGHT_ID": 28,
      "SOURCE_FILE_NAME": "10552_NYU_M2 - Scanner 1 - 190511_170520_1 - originalpoints.las",
      "NUMBER_OF_POINTS": 12453803,
      "START_TIMESTAMP": "0000-01-01T00:00:00.000Z",
      "TIME_TAG": "170520"
    },
    {
      "SOURCE_FILE_CREATION_DATE": "2019-08-20T00:00:00.000Z",
      "FLIGHT_ID": 29,
      "SOURCE_FILE_NAME": "10552_NYU_M2 - Scanner 1 - 190511_170643_1 - originalpoints.las",
      "NUMBER_OF_POINTS": 15018408,
      "START_TIMESTAMP": "0000-01-01T00:00:00.000Z",
      "TIME_TAG": "170643"
    },
    {
      "SOURCE_FILE_CREATION_DATE": "2019-08-20T00:00:00.000Z",
      "FLIGHT_ID": 30,
      "SOURCE_FILE_NAME": "10552_NYU_M2 - Scanner 1 - 190511_170840_1 - originalpoints.las",
      "NUMBER_OF_POINTS": 17692931,
      "START_TIMESTAMP": "0000-01-01T00:00:00.000Z",
      "TIME_TAG": "170840"
    },
    {
      "SOURCE_FILE_CREATION_DATE": "2019-08-20T00:00:00.000Z",
      "FLIGHT_ID": 32,
      "SOURCE_FILE_NAME": "10552_NYU_M2 - Scanner 1 - 190511_171225_1 - originalpoints.las",
      "NUMBER_OF_POINTS": 17845243,
      "START_TIMESTAMP": "0000-01-01T00:00:00.000Z",
      "TIME_TAG": "171225"
    },
    {
      "SOURCE_FILE_CREATION_DATE": "2019-08-20T00:00:00.000Z",
      "FLIGHT_ID": 33,
      "SOURCE_FILE_NAME": "10552_NYU_M2 - Scanner 1 - 190511_171348_1 - originalpoints.las",
      "NUMBER_OF_POINTS": 14277681,
      "START_TIMESTAMP": "0000-01-01T00:00:00.000Z",
      "TIME_TAG": "171348"
    },
    {
      "SOURCE_FILE_CREATION_DATE": "2019-08-20T00:00:00.000Z",
      "FLIGHT_ID": 34,
      "SOURCE_FILE_NAME": "10552_NYU_M2 - Scanner 1 - 190511_171553_1 - originalpoints.las",
      "NUMBER_OF_POINTS": 23213177,
      "START_TIMESTAMP": "0000-01-01T00:00:00.000Z",
      "TIME_TAG": "171553"
    },
    {
      "SOURCE_FILE_CREATION_DATE": "2019-08-20T00:00:00.000Z",
      "FLIGHT_ID": 35,
      "SOURCE_FILE_NAME": "10552_NYU_M2 - Scanner 1 - 190511_171754_1 - originalpoints.las",
      "NUMBER_OF_POINTS": 22224630,
      "START_TIMESTAMP": "0000-01-01T00:00:00.000Z",
      "TIME_TAG": "171754"
    },
    {
      "SOURCE_FILE_CREATION_DATE": "2019-08-20T00:00:00.000Z",
      "FLIGHT_ID": 36,
      "SOURCE_FILE_NAME": "10552_NYU_M2 - Scanner 1 - 190511_172007_1 - originalpoints.las",
      "NUMBER_OF_POINTS": 19682423,
      "START_TIMESTAMP": "0000-01-01T00:00:00.000Z",
      "TIME_TAG": "172007"
    },
    {
      "SOURCE_FILE_CREATION_DATE": "2019-08-20T00:00:00.000Z",
      "FLIGHT_ID": 37,
      "SOURCE_FILE_NAME": "10552_NYU_M2 - Scanner 1 - 190511_172201_1 - originalpoints.las",
      "NUMBER_OF_POINTS": 18942131,
      "START_TIMESTAMP": "0000-01-01T00:00:00.000Z",
      "TIME_TAG": "172201"
    },
    {
      "SOURCE_FILE_CREATION_DATE": "2019-08-20T00:00:00.000Z",
      "FLIGHT_ID": 38,
      "SOURCE_FILE_NAME": "10552_NYU_M2 - Scanner 1 - 190511_172416_1 - originalpoints.las",
      "NUMBER_OF_POINTS": 17095931,
      "START_TIMESTAMP": "0000-01-01T00:00:00.000Z",
      "TIME_TAG": "172416"
    },
    {
      "SOURCE_FILE_CREATION_DATE": "2019-08-20T00:00:00.000Z",
      "FLIGHT_ID": 39,
      "SOURCE_FILE_NAME": "10552_NYU_M2 - Scanner 1 - 190511_172558_1 - originalpoints.las",
      "NUMBER_OF_POINTS": 13746833,
      "START_TIMESTAMP": "0000-01-01T00:00:00.000Z",
      "TIME_TAG": "172558"
    },
    {
      "SOURCE_FILE_CREATION_DATE": "2019-08-20T00:00:00.000Z",
      "FLIGHT_ID": 40,
      "SOURCE_FILE_NAME": "10552_NYU_M2 - Scanner 1 - 190511_172753_1 - originalpoints.las",
      "NUMBER_OF_POINTS": 12028738,
      "START_TIMESTAMP": "0000-01-01T00:00:00.000Z",
      "TIME_TAG": "172753"
    },
    {
      "SOURCE_FILE_CREATION_DATE": "2019-08-20T00:00:00.000Z",
      "FLIGHT_ID": 42,
      "SOURCE_FILE_NAME": "10552_NYU_M2 - Scanner 1 - 190511_173110_1 - originalpoints.las",
      "NUMBER_OF_POINTS": 9587059,
      "START_TIMESTAMP": "0000-01-01T00:00:00.000Z",
      "TIME_TAG": "173110"
    },
    {
      "SOURCE_FILE_CREATION_DATE": "2019-08-20T00:00:00.000Z",
      "FLIGHT_ID": 43,
      "SOURCE_FILE_NAME": "10552_NYU_M2 - Scanner 1 - 190511_173238_1 - originalpoints.las",
      "NUMBER_OF_POINTS": 7979263,
      "START_TIMESTAMP": "0000-01-01T00:00:00.000Z",
      "TIME_TAG": "173238"
    },
    {
      "SOURCE_FILE_CREATION_DATE": "2019-08-20T00:00:00.000Z",
      "FLIGHT_ID": 44,
      "SOURCE_FILE_NAME": "10552_NYU_M2 - Scanner 1 - 190511_173415_1 - originalpoints.las",
      "NUMBER_OF_POINTS": 6167650,
      "START_TIMESTAMP": "0000-01-01T00:00:00.000Z",
      "TIME_TAG": "173415"
    },
    {
      "SOURCE_FILE_CREATION_DATE": "2019-08-20T00:00:00.000Z",
      "FLIGHT_ID": 45,
      "SOURCE_FILE_NAME": "10552_NYU_M2 - Scanner 1 - 190511_173536_1 - originalpoints.las",
      "NUMBER_OF_POINTS": 4525533,
      "START_TIMESTAMP": "0000-01-01T00:00:00.000Z",
      "TIME_TAG": "173536"
    },
    {
      "SOURCE_FILE_CREATION_DATE": "2019-08-20T00:00:00.000Z",
      "FLIGHT_ID": 46,
      "SOURCE_FILE_NAME": "10552_NYU_M2 - Scanner 1 - 190511_173707_1 - originalpoints.las",
      "NUMBER_OF_POINTS": 3158054,
      "START_TIMESTAMP": "0000-01-01T00:00:00.000Z",
      "TIME_TAG": "173707"
    },
    {
      "SOURCE_FILE_CREATION_DATE": "2019-08-20T00:00:00.000Z",
      "FLIGHT_ID": 47,
      "SOURCE_FILE_NAME": "10552_NYU_M2 - Scanner 1 - 190511_174013_1 - originalpoints.las",
      "NUMBER_OF_POINTS": 9039989,
      "START_TIMESTAMP": "0000-01-01T00:00:00.000Z",
      "TIME_TAG": "174013"
    },
    {
      "SOURCE_FILE_CREATION_DATE": "2019-08-20T00:00:00.000Z",
      "FLIGHT_ID": 48,
      "SOURCE_FILE_NAME": "10552_NYU_M2 - Scanner 1 - 190511_174133_1 - originalpoints.las",
      "NUMBER_OF_POINTS": 14454374,
      "START_TIMESTAMP": "0000-01-01T00:00:00.000Z",
      "TIME_TAG": "174133"
    },
    {
      "SOURCE_FILE_CREATION_DATE": "2019-08-20T00:00:00.000Z",
      "FLIGHT_ID": 49,
      "SOURCE_FILE_NAME": "10552_NYU_M2 - Scanner 1 - 190511_174333_1 - originalpoints.las",
      "NUMBER_OF_POINTS": 15234959,
      "START_TIMESTAMP": "0000-01-01T00:00:00.000Z",
      "TIME_TAG": "174333"
    },
    {
      "SOURCE_FILE_CREATION_DATE": "2019-08-20T00:00:00.000Z",
      "FLIGHT_ID": 50,
      "SOURCE_FILE_NAME": "10552_NYU_M2 - Scanner 1 - 190511_174515_1 - originalpoints.las",
      "NUMBER_OF_POINTS": 17140943,
      "START_TIMESTAMP": "0000-01-01T00:00:00.000Z",
      "TIME_TAG": "174515"
    },
    {
      "SOURCE_FILE_CREATION_DATE": "2019-08-20T00:00:00.000Z",
      "FLIGHT_ID": 52,
      "SOURCE_FILE_NAME": "10552_NYU_M2 - Scanner 1 - 190511_174919_1 - originalpoints.las",
      "NUMBER_OF_POINTS": 16813332,
      "START_TIMESTAMP": "0000-01-01T00:00:00.000Z",
      "TIME_TAG": "174919"
    },
    {
      "SOURCE_FILE_CREATION_DATE": "2019-08-20T00:00:00.000Z",
      "FLIGHT_ID": 53,
      "SOURCE_FILE_NAME": "10552_NYU_M2 - Scanner 1 - 190511_175125_1 - originalpoints.las",
      "NUMBER_OF_POINTS": 18706600,
      "START_TIMESTAMP": "0000-01-01T00:00:00.000Z",
      "TIME_TAG": "175125"
    },
    {
      "SOURCE_FILE_CREATION_DATE": "2019-08-20T00:00:00.000Z",
      "FLIGHT_ID": 54,
      "SOURCE_FILE_NAME": "10552_NYU_M2 - Scanner 1 - 190511_175315_1 - originalpoints.las",
      "NUMBER_OF_POINTS": 15483251,
      "START_TIMESTAMP": "0000-01-01T00:00:00.000Z",
      "TIME_TAG": "175315"
    },
    {
      "SOURCE_FILE_CREATION_DATE": "2019-08-20T00:00:00.000Z",
      "FLIGHT_ID": 55,
      "SOURCE_FILE_NAME": "10552_NYU_M2 - Scanner 1 - 190511_175503_1 - originalpoints.las",
      "NUMBER_OF_POINTS": 18040814,
      "START_TIMESTAMP": "0000-01-01T00:00:00.000Z",
      "TIME_TAG": "175503"
    },
    {
      "SOURCE_FILE_CREATION_DATE": "2019-08-20T00:00:00.000Z",
      "FLIGHT_ID": 56,
      "SOURCE_FILE_NAME": "10552_NYU_M2 - Scanner 1 - 190511_175659_1 - originalpoints.las",
      "NUMBER_OF_POINTS": 15333291,
      "START_TIMESTAMP": "0000-01-01T00:00:00.000Z",
      "TIME_TAG": "175659"
    },
    {
      "SOURCE_FILE_CREATION_DATE": "2019-08-20T00:00:00.000Z",
      "FLIGHT_ID": 57,
      "SOURCE_FILE_NAME": "10552_NYU_M2 - Scanner 1 - 190511_175842_1 - originalpoints.las",
      "NUMBER_OF_POINTS": 20888042,
      "START_TIMESTAMP": "0000-01-01T00:00:00.000Z",
      "TIME_TAG": "175842"
    },
    {
      "SOURCE_FILE_CREATION_DATE": "2019-08-20T00:00:00.000Z",
      "FLIGHT_ID": 58,
      "SOURCE_FILE_NAME": "10552_NYU_M2 - Scanner 1 - 190511_180048_1 - originalpoints.las",
      "NUMBER_OF_POINTS": 13199642,
      "START_TIMESTAMP": "0000-01-01T00:00:00.000Z",
      "TIME_TAG": "180048"
    },
    {
      "SOURCE_FILE_CREATION_DATE": "2019-08-20T00:00:00.000Z",
      "FLIGHT_ID": 59,
      "SOURCE_FILE_NAME": "10552_NYU_M2 - Scanner 1 - 190511_180231_1 - originalpoints.las",
      "NUMBER_OF_POINTS": 18624019,
      "START_TIMESTAMP": "0000-01-01T00:00:00.000Z",
      "TIME_TAG": "180231"
    },
    {
      "SOURCE_FILE_CREATION_DATE": "2019-08-20T00:00:00.000Z",
      "FLIGHT_ID": 60,
      "SOURCE_FILE_NAME": "10552_NYU_M2 - Scanner 1 - 190511_180428_1 - originalpoints.las",
      "NUMBER_OF_POINTS": 19245867,
      "START_TIMESTAMP": "0000-01-01T00:00:00.000Z",
      "TIME_TAG": "180428"
    },
    {
      "SOURCE_FILE_CREATION_DATE": "2019-08-20T00:00:00.000Z",
      "FLIGHT_ID": 11,
      "SOURCE_FILE_NAME": "10552_NYU_M2 - Scanner 1 - 190511_163425_1 - originalpoints.las",
      "NUMBER_OF_POINTS": 21882557,
      "START_TIMESTAMP": "0000-01-01T00:00:00.000Z",
      "TIME_TAG": "163425"
    },
    {
      "SOURCE_FILE_CREATION_DATE": "2019-08-20T00:00:00.000Z",
      "FLIGHT_ID": 21,
      "SOURCE_FILE_NAME": "10552_NYU_M2 - Scanner 1 - 190511_165342_1 - originalpoints.las",
      "NUMBER_OF_POINTS": 9214701,
      "START_TIMESTAMP": "0000-01-01T00:00:00.000Z",
      "TIME_TAG": "165342"
    },
    {
      "SOURCE_FILE_CREATION_DATE": "2019-08-20T00:00:00.000Z",
      "FLIGHT_ID": 31,
      "SOURCE_FILE_NAME": "10552_NYU_M2 - Scanner 1 - 190511_171015_1 - originalpoints.las",
      "NUMBER_OF_POINTS": 16715240,
      "START_TIMESTAMP": "0000-01-01T00:00:00.000Z",
      "TIME_TAG": "171015"
    },
    {
      "SOURCE_FILE_CREATION_DATE": "2019-08-20T00:00:00.000Z",
      "FLIGHT_ID": 41,
      "SOURCE_FILE_NAME": "10552_NYU_M2 - Scanner 1 - 190511_172928_1 - originalpoints.las",
      "NUMBER_OF_POINTS": 8391238,
      "START_TIMESTAMP": "0000-01-01T00:00:00.000Z",
      "TIME_TAG": "172928"
    },
    {
      "SOURCE_FILE_CREATION_DATE": "2019-08-20T00:00:00.000Z",
      "FLIGHT_ID": 51,
      "SOURCE_FILE_NAME": "10552_NYU_M2 - Scanner 1 - 190511_174725_1 - originalpoints.las",
      "NUMBER_OF_POINTS": 21556176,
      "START_TIMESTAMP": "0000-01-01T00:00:00.000Z",
      "TIME_TAG": "174725"
    },
    {
      "SOURCE_FILE_CREATION_DATE": "2019-08-20T00:00:00.000Z",
      "FLIGHT_ID": 61,
      "SOURCE_FILE_NAME": "10552_NYU_M2 - Scanner 1 - 190511_180632_1 - originalpoints.las",
      "NUMBER_OF_POINTS": 15229134,
      "START_TIMESTAMP": "0000-01-01T00:00:00.000Z",
      "TIME_TAG": "180632"
    },
    {
      "SOURCE_FILE_CREATION_DATE": "2019-08-20T00:00:00.000Z",
      "FLIGHT_ID": 81,
      "SOURCE_FILE_NAME": "10552_NYU_M3 - Scanner 1 - 190511_194904_1 - originalpoints.las",
      "NUMBER_OF_POINTS": 17943842,
      "START_TIMESTAMP": "0000-01-01T00:00:00.000Z",
      "TIME_TAG": "194904"
    },
    {
      "SOURCE_FILE_CREATION_DATE": "2019-08-20T00:00:00.000Z",
      "FLIGHT_ID": 74,
      "SOURCE_FILE_NAME": "10552_NYU_M3 - Scanner 1 - 190511_200212_1 - originalpoints.las",
      "NUMBER_OF_POINTS": 11891832,
      "START_TIMESTAMP": "0000-01-01T00:00:00.000Z",
      "TIME_TAG": "200212"
    },
    {
      "SOURCE_FILE_CREATION_DATE": "2019-08-20T00:00:00.000Z",
      "FLIGHT_ID": 62,
      "SOURCE_FILE_NAME": "10552_NYU_M2 - Scanner 1 - 190511_180819_1 - originalpoints.las",
      "NUMBER_OF_POINTS": 12975724,
      "START_TIMESTAMP": "0000-01-01T00:00:00.000Z",
      "TIME_TAG": "180819"
    },
    {
      "SOURCE_FILE_CREATION_DATE": "2019-08-20T00:00:00.000Z",
      "FLIGHT_ID": 63,
      "SOURCE_FILE_NAME": "10552_NYU_M2 - Scanner 1 - 190511_181004_1 - originalpoints.las",
      "NUMBER_OF_POINTS": 13244197,
      "START_TIMESTAMP": "0000-01-01T00:00:00.000Z",
      "TIME_TAG": "181004"
    },
    {
      "SOURCE_FILE_CREATION_DATE": "2019-08-20T00:00:00.000Z",
      "FLIGHT_ID": 64,
      "SOURCE_FILE_NAME": "10552_NYU_M2 - Scanner 1 - 190511_181155_1 - originalpoints.las",
      "NUMBER_OF_POINTS": 8654250,
      "START_TIMESTAMP": "0000-01-01T00:00:00.000Z",
      "TIME_TAG": "181155"
    },
    {
      "SOURCE_FILE_CREATION_DATE": "2019-08-20T00:00:00.000Z",
      "FLIGHT_ID": 65,
      "SOURCE_FILE_NAME": "10552_NYU_M2 - Scanner 1 - 190511_181332_1 - originalpoints.las",
      "NUMBER_OF_POINTS": 5960295,
      "START_TIMESTAMP": "0000-01-01T00:00:00.000Z",
      "TIME_TAG": "181332"
    },
    {
      "SOURCE_FILE_CREATION_DATE": "2019-08-20T00:00:00.000Z",
      "FLIGHT_ID": 66,
      "SOURCE_FILE_NAME": "10552_NYU_M3 - Scanner 1 - 190511_194021_1 - originalpoints.las",
      "NUMBER_OF_POINTS": 6583748,
      "START_TIMESTAMP": "0000-01-01T00:00:00.000Z",
      "TIME_TAG": "194021"
    },
    {
      "SOURCE_FILE_CREATION_DATE": "2019-08-20T00:00:00.000Z",
      "FLIGHT_ID": 85,
      "SOURCE_FILE_NAME": "10552_NYU_M3 - Scanner 1 - 190511_194139_1 - originalpoints.las",
      "NUMBER_OF_POINTS": 1881882,
      "START_TIMESTAMP": "0000-01-01T00:00:00.000Z",
      "TIME_TAG": "194139"
    },
    {
      "SOURCE_FILE_CREATION_DATE": "2019-08-20T00:00:00.000Z",
      "FLIGHT_ID": 84,
      "SOURCE_FILE_NAME": "10552_NYU_M3 - Scanner 1 - 190511_194310_1 - originalpoints.las",
      "NUMBER_OF_POINTS": 5744543,
      "START_TIMESTAMP": "0000-01-01T00:00:00.000Z",
      "TIME_TAG": "194310"
    },
    {
      "SOURCE_FILE_CREATION_DATE": "2019-08-20T00:00:00.000Z",
      "FLIGHT_ID": 83,
      "SOURCE_FILE_NAME": "10552_NYU_M3 - Scanner 1 - 190511_194446_1 - originalpoints.las",
      "NUMBER_OF_POINTS": 15253031,
      "START_TIMESTAMP": "0000-01-01T00:00:00.000Z",
      "TIME_TAG": "194446"
    },
    {
      "SOURCE_FILE_CREATION_DATE": "2019-08-20T00:00:00.000Z",
      "FLIGHT_ID": 82,
      "SOURCE_FILE_NAME": "10552_NYU_M3 - Scanner 1 - 190511_194702_1 - originalpoints.las",
      "NUMBER_OF_POINTS": 21275007,
      "START_TIMESTAMP": "0000-01-01T00:00:00.000Z",
      "TIME_TAG": "194702"
    },
    {
      "SOURCE_FILE_CREATION_DATE": "2019-08-20T00:00:00.000Z",
      "FLIGHT_ID": 80,
      "SOURCE_FILE_NAME": "10552_NYU_M3 - Scanner 1 - 190511_195058_1 - originalpoints.las",
      "NUMBER_OF_POINTS": 17157234,
      "START_TIMESTAMP": "0000-01-01T00:00:00.000Z",
      "TIME_TAG": "195058"
    },
    {
      "SOURCE_FILE_CREATION_DATE": "2019-08-20T00:00:00.000Z",
      "FLIGHT_ID": 79,
      "SOURCE_FILE_NAME": "10552_NYU_M3 - Scanner 1 - 190511_195235_1 - originalpoints.las",
      "NUMBER_OF_POINTS": 14939429,
      "START_TIMESTAMP": "0000-01-01T00:00:00.000Z",
      "TIME_TAG": "195235"
    },
    {
      "SOURCE_FILE_CREATION_DATE": "2019-08-20T00:00:00.000Z",
      "FLIGHT_ID": 78,
      "SOURCE_FILE_NAME": "10552_NYU_M3 - Scanner 1 - 190511_195448_1 - originalpoints.las",
      "NUMBER_OF_POINTS": 18377032,
      "START_TIMESTAMP": "0000-01-01T00:00:00.000Z",
      "TIME_TAG": "195448"
    },
    {
      "SOURCE_FILE_CREATION_DATE": "2019-08-20T00:00:00.000Z",
      "FLIGHT_ID": 77,
      "SOURCE_FILE_NAME": "10552_NYU_M3 - Scanner 1 - 190511_195634_1 - originalpoints.las",
      "NUMBER_OF_POINTS": 15879084,
      "START_TIMESTAMP": "0000-01-01T00:00:00.000Z",
      "TIME_TAG": "195634"
    },
    {
      "SOURCE_FILE_CREATION_DATE": "2019-08-20T00:00:00.000Z",
      "FLIGHT_ID": 76,
      "SOURCE_FILE_NAME": "10552_NYU_M3 - Scanner 1 - 190511_195833_1 - originalpoints.las",
      "NUMBER_OF_POINTS": 15651994,
      "START_TIMESTAMP": "0000-01-01T00:00:00.000Z",
      "TIME_TAG": "195833"
    },
    {
      "SOURCE_FILE_CREATION_DATE": "2019-08-20T00:00:00.000Z",
      "FLIGHT_ID": 75,
      "SOURCE_FILE_NAME": "10552_NYU_M3 - Scanner 1 - 190511_200024_1 - originalpoints.las",
      "NUMBER_OF_POINTS": 12950543,
      "START_TIMESTAMP": "0000-01-01T00:00:00.000Z",
      "TIME_TAG": "200024"
    },
    {
      "SOURCE_FILE_CREATION_DATE": "2019-08-20T00:00:00.000Z",
      "FLIGHT_ID": 73,
      "SOURCE_FILE_NAME": "10552_NYU_M3 - Scanner 1 - 190511_200348_1 - originalpoints.las",
      "NUMBER_OF_POINTS": 14162455,
      "START_TIMESTAMP": "0000-01-01T00:00:00.000Z",
      "TIME_TAG": "200348"
    },
    {
      "SOURCE_FILE_CREATION_DATE": "2019-08-20T00:00:00.000Z",
      "FLIGHT_ID": 72,
      "SOURCE_FILE_NAME": "10552_NYU_M3 - Scanner 1 - 190511_200600_1 - originalpoints.las",
      "NUMBER_OF_POINTS": 13381511,
      "START_TIMESTAMP": "0000-01-01T00:00:00.000Z",
      "TIME_TAG": "200600"
    },
    {
      "SOURCE_FILE_CREATION_DATE": "2019-08-20T00:00:00.000Z",
      "FLIGHT_ID": 71,
      "SOURCE_FILE_NAME": "10552_NYU_M3 - Scanner 1 - 190511_200742_1 - originalpoints.las",
      "NUMBER_OF_POINTS": 13774280,
      "START_TIMESTAMP": "0000-01-01T00:00:00.000Z",
      "TIME_TAG": "200742"
    },
    {
      "SOURCE_FILE_CREATION_DATE": "2019-08-20T00:00:00.000Z",
      "FLIGHT_ID": 70,
      "SOURCE_FILE_NAME": "10552_NYU_M3 - Scanner 1 - 190511_200938_1 - originalpoints.las",
      "NUMBER_OF_POINTS": 13519706,
      "START_TIMESTAMP": "0000-01-01T00:00:00.000Z",
      "TIME_TAG": "200938"
    },
    {
      "SOURCE_FILE_CREATION_DATE": "2019-08-20T00:00:00.000Z",
      "FLIGHT_ID": 69,
      "SOURCE_FILE_NAME": "10552_NYU_M3 - Scanner 1 - 190511_201120_1 - originalpoints.las",
      "NUMBER_OF_POINTS": 15608886,
      "START_TIMESTAMP": "0000-01-01T00:00:00.000Z",
      "TIME_TAG": "201120"
    },
    {
      "SOURCE_FILE_CREATION_DATE": "2019-08-20T00:00:00.000Z",
      "FLIGHT_ID": 68,
      "SOURCE_FILE_NAME": "10552_NYU_M3 - Scanner 1 - 190511_201329_1 - originalpoints.las",
      "NUMBER_OF_POINTS": 17834902,
      "START_TIMESTAMP": "0000-01-01T00:00:00.000Z",
      "TIME_TAG": "201329"
    },
    {
      "SOURCE_FILE_CREATION_DATE": "2019-08-20T00:00:00.000Z",
      "FLIGHT_ID": 67,
      "SOURCE_FILE_NAME": "10552_NYU_M3 - Scanner 1 - 190511_201532_1 - originalpoints.las",
      "NUMBER_OF_POINTS": 12622763,
      "START_TIMESTAMP": "0000-01-01T00:00:00.000Z",
      "TIME_TAG": "201532"
    }
  ],
  "OFFSET": [
    977000,
    173000,
    0,
    0
  ],
  "LAS_HEADER": "4c415346010010000000000000000000000000000000000001044c4153746f6f6c73202863292062792072617069646c6173736f20476d6248006c6173326c6173202876657273696f6e20313930383132290000000000000000e800e30777010002000001000000061e00000000000000000000000000000000000000000000000000fca9f1d24d62503ffca9f1d24d62503ffca9f1d24d62503f00000000d0d02d4100000000401e05410000000000000000f0a7c60ba5f12d411f85eb1197e42d415a643bdf084a05418716d9ce22100541560e2db29d5e8740d122dbf97eb47fc00000000000000000000000000000000000000000890c6b00000000005564570000000000313b0d0000000000627f040000000000bf77010000000000b55e00000000000039130000000000005f030000000000007e00000000000000160000000000000001000000000000000000000000000000000000000000000000000000000000000000000000000000000000000000000000004c4153465f50726f6a656374696f6e00af87400047656f546966662050726f6a656374696f6e204b657973000000000000000000010001000000040000040000010001000104000001000100000c00000100ff7f040c000001002b23000000000000000000000000000000000000000000000000",
  "SCALE": [
    0.001,
    0.001,
    0.001,
    0.0000010
  ],
  "SRID": 2263,
  "LAS_VERSION": [
    1,
    4,
    6
  ],
  "PROJECT_NAME": "Sunset Park 2019-05"
}